gpt_editor_utils/__init__.py
gpt_editor_utils/config.py
gpt_editor_utils/html_to_claude_chat_list.py
gpt_editor_utils/html_to_gpts_list.py
gpt_editor_utils/pdf_to_text_from_moodle_dl_dir.py
gpt_editor_utils/utils.py
gpt_editor_utils-0.1.4.dist-info/METADATA
gpt_editor_utils-0.1.4.dist-info/WHEEL
gpt_editor_utils-0.1.4.dist-info/entry_points.txt
gpt_editor_utils-0.1.4.dist-info/RECORD
